[ {
  "singleVerses" : [ "luke,7,36" ],
  "rsbNotes" : [ ]
}, {
  "singleVerses" : [ "luke,7,37" ],
  "rsbNotes" : [ {
    "verseRange" : "luke,7,37-luke,7,38",
    "id" : 196469,
    "title" : "Luke 7:37–38",
    "text" : "<div class=\"article\"><p><b><a class=\"bibleref\" href=\"/passage/?search=Luke 7:37\">7:37</a>, <a class=\"bibleref\" href=\"/passage/?search=Luke 7:38\">38</a></b> At a dinner like this the house would be open and people could come in and watch. A sinful woman (perhaps a prostitute) would not have been welcome; it took courage for her to come. Guests at dinner reclined on couches. Leaning on the left side, they took the food with their right hands.</p></div>"
  }, {
    "verseRange" : "luke,7,37",
    "id" : 196470,
    "title" : "Luke 7:37",
    "text" : "<div class=\"article\"><p><b><a class=\"bibleref\" href=\"/passage/?search=Luke 7:37\">7:37</a></b> <b>alabaster.</b> A translucent stone used to make containers for costly perfumes.</p></div>"
  } ]
}, {
  "singleVerses" : [ "luke,7,38" ],
  "rsbNotes" : [ {
    "verseRange" : "luke,7,38",
    "id" : 196471,
    "title" : "Luke 7:38",
    "text" : "<div class=\"article\"><p><b><a class=\"bibleref\" href=\"/passage/?search=Luke 7:38\">7:38</a></b> <b>weeping.</b> The woman’s tears and her anointing of Jesus’ feet demonstrated penitence and humility.</p></div>"
  } ]
}, {
  "singleVerses" : [ "luke,7,39", "luke,7,40", "luke,7,41", "luke,7,42", "luke,7,43" ],
  "rsbNotes" : [ {
    "verseRange" : "luke,7,39",
    "id" : 196472,
    "title" : "Luke 7:39",
    "text" : "<div class=\"article\"><p><b><a class=\"bibleref\" href=\"/passage/?search=Luke 7:39\">7:39</a></b> <b>this man . . . would have known.</b> A Pharisee would have no contact with sinful people, and was sure that no prophet would have such contact either. As Jesus did not dismiss the woman, Simon thought that He either did not know that she was sinful or did not care. In either case, in Simon’s view Jesus could not be a prophet.</p></div>"
  } ]
}, {
  "singleVerses" : [ "luke,7,44", "luke,7,45", "luke,7,46" ],
  "rsbNotes" : [ {
    "verseRange" : "luke,7,44-luke,7,46",
    "id" : 196473,
    "title" : "Luke 7:44–46",
    "text" : "<div class=\"article\"><p><b><a class=\"bibleref\" href=\"/passage/?search=Luke 7:44-Luke 7:46\">7:44–46</a></b> Simon had omitted the courtesies normally given to guests. But the woman made up for this.</p></div>"
  } ]
}, {
  "singleVerses" : [ "luke,7,47" ],
  "rsbNotes" : [ {
    "verseRange" : "luke,7,47",
    "id" : 196474,
    "title" : "Luke 7:47",
    "text" : "<div class=\"article\"><p><b><a class=\"bibleref\" href=\"/passage/?search=Luke 7:47\">7:47</a></b> <b>for.</b> The woman was forgiven because of faith (<a class=\"bibleref\" href=\"/passage/?search=Luke 7:50\">v. 50</a>). Her love showed that she understood what God’s forgiveness meant for her.</p></div>"
  } ]
}, {
  "singleVerses" : [ "luke,7,48", "luke,7,49", "luke,7,50", "luke,8,1" ],
  "rsbNotes" : [ {
    "verseRange" : "luke,7,48-luke,7,50",
    "id" : 196475,
    "title" : "Luke 7:48–50",
    "text" : "<div class=\"article\"><p><b><a class=\"bibleref\" href=\"/passage/?search=Luke 7:48-Luke 7:50\">7:48–50</a></b> Again Jesus authoritatively declares sins to be forgiven, an act that arouses comment (cf. <a class=\"bibleref\" href=\"/passage/?search=Luke 5:20\">5:20</a>, <a class=\"bibleref\" href=\"/passage/?search=Luke 5:21\">21</a>). But His concern is for the woman.</p></div>"
  } ]
}, {
  "singleVerses" : [ "luke,8,2" ],
  "rsbNotes" : [ {
    "verseRange" : "luke,8,2",
    "id" : 196476,
    "title" : "Luke 8:2",
    "text" : "<div class=\"article\"><p><b><a class=\"bibleref\" href=\"/passage/?search=Luke 8:2\">8:2</a></b> Rabbis refused to teach women, so Jesus’ acceptance of them into His group of followers was unusual.</p><p><b>Magdalene.</b> From the town of Magdala.</p></div>"
  } ]
}, {
  "singleVerses" : [ "luke,8,3" ],
  "rsbNotes" : [ {
    "verseRange" : "luke,8,3",
    "id" : 196477,
    "title" : "Luke 8:3",
    "text" : "<div class=\"article\"><p><b><a class=\"bibleref\" href=\"/passage/?search=Luke 8:3\">8:3</a></b> <b>out of their means.</b> This provides a glimpse of the way Jesus and His band were supported throughout His ministry.</p></div>"
  } ]
} ]
