[ {
  "singleVerses" : [ "acts,1,1" ],
  "rsbNotes" : [ {
    "verseRange" : "acts,1,1",
    "id" : 197345,
    "title" : "Acts 1:1",
    "text" : "<div class=\"article\"><p><b><a class=\"bibleref\" href=\"/passage/?search=Acts 1:1\">1:1</a></b> <b>In the first book.</b> The Gospel of Luke as shown by the reference to Theophilus (<a class=\"bibleref\" href=\"/passage/?search=Luke 1:3\">Luke 1:3</a>).</p><p><b>all that Jesus began to do and teach.</b> A fitting summary of what Luke records in the Gospel.</p></div>"
  } ]
}, {
  "singleVerses" : [ "acts,1,2" ],
  "rsbNotes" : [ {
    "verseRange" : "acts,1,2",
    "id" : 197346,
    "title" : "Acts 1:2",
    "text" : "<div class=\"article\"><p><b><a class=\"bibleref\" href=\"/passage/?search=Acts 1:2\">1:2</a></b> <b>taken up.</b> <a class=\"bibleref\" href=\"/passage/?search=Luke 24:50-Luke 24:52\">Luke 24:50–52</a> locates the Ascension near Bethany, on the east side of the Mount of Olives, east of Jerusalem.</p><p><b>commands through the Holy Spirit.</b> After the Resurrection Jesus communicated to His apostles the reality of His resurrection (<a class=\"bibleref\" href=\"/passage/?search=John 20\">John 20</a>; <a class=\"bibleref\" href=\"/passage/?search=John 21\">21</a>), the truth of His calling as Messiah (<a class=\"bibleref\" href=\"/passage/?search=Luke 24:44-Luke 24:49\">Luke 24:44–49</a>), the blessing of the Holy Spirit (<a class=\"bibleref\" href=\"/passage/?search=John 20:22\">John 20:22</a>, <a class=\"bibleref\" href=\"/passage/?search=John 20:23\">23</a>), and the reality of His physical resurrection body (<a class=\"bibleref\" href=\"/passage/?search=Luke 24:37-Luke 24:43\">Luke 24:37–43</a>).</p><p><b>he had chosen.</b> A reference to Jesus’ original choice of His apostles (<a class=\"bibleref\" href=\"/passage/?search=Luke 6:12-Luke 6:16\">Luke 6:12–16</a>), one of whom (Judas) Jesus knew would become a traitor.</p></div>"
  } ]
}, {
  "singleVerses" : [ "acts,1,3" ],
  "rsbNotes" : [ {
    "verseRange" : "acts,1,3",
    "id" : 197347,
    "title" : "Acts 1:3",
    "text" : "<div class=\"article\"><p><b><a class=\"bibleref\" href=\"/passage/?search=Acts 1:3\">1:3</a></b> <b>presented himself . . . many proofs.</b> Christ’s resurrection appearances (<a class=\"bibleref\" href=\"/passage/?search=Matt 28\">Matt. 28</a>; <a class=\"bibleref\" href=\"/passage/?search=Mark 16\">Mark 16</a>; <a class=\"bibleref\" href=\"/passage/?search=Luke 24\">Luke 24</a>; <a class=\"bibleref\" href=\"/passage/?search=John 20\">John 20</a>; <a class=\"bibleref\" href=\"/passage/?search=John 21\">21</a>; <a class=\"bibleref\" href=\"/passage/?search=1Cor 15:5-1Cor 15:7\">1 Cor. 15:5–7</a>) were important as an unshakable confirmation of Christ’s supernatural person and work. It was important that Jesus’ resurrection should be seen by the disciples (v. 22).</p><p><b>forty days.</b> The time from the Resurrection to the Ascension. After Jesus ascended to heaven, the disciples stayed ten days in Jerusalem waiting for the promised outpouring of the Holy Spirit that occurred on Pentecost, the fiftieth day after Passover.</p></div>"
  } ]
}, {
  "singleVerses" : [ "acts,1,4" ],
  "rsbNotes" : [ {
    "verseRange" : "acts,1,4",
    "id" : 197348,
    "title" : "Acts 1:4",
    "text" : "<div class=\"article\"><p><b><a class=\"bibleref\" href=\"/passage/?search=Acts 1:4\">1:4</a></b> <b>while staying with them.</b> Jesus often communed with His friends and disciples over a meal: at the feeding of the five thousand (<a class=\"bibleref\" href=\"/passage/?search=Luke 9:16\">Luke 9:16</a>), with tax collectors and sinners (<a class=\"bibleref\" href=\"/passage/?search=Mark 2:15\">Mark 2:15</a>, <a class=\"bibleref\" href=\"/passage/?search=Mark 2:16\">16</a>; <a class=\"bibleref\" href=\"/passage/?search=Luke 5:29\">Luke 5:29</a>), at the Pharisee’s house (<a class=\"bibleref\" href=\"/passage/?search=Luke 7:37\">Luke 7:37</a>), at the Last Supper (<a class=\"bibleref\" href=\"/passage/?search=Matt 26:21\">Matt. 26:21</a>, <a class=\"bibleref\" href=\"/passage/?search=Matt 26:26\">26</a>), and after the Resurrection (<a class=\"bibleref\" href=\"/passage/?search=Luke 24:42\">Luke 24:42</a>; <a class=\"bibleref\" href=\"/passage/?search=John 21:9-John 21:15\">John 21:9–15</a>).</p><p><b>wait for the promise of the Father.</b> The Holy Spirit was the gift of the Father and the gift of Jesus the Son (<a class=\"bibleref\" href=\"/passage/?search=John 14:1\">John 14:1</a>, <a class=\"bibleref\" href=\"/passage/?search=John 14:26\">26</a>; <a class=\"bibleref\" href=\"/passage/?search=John 15:26\">15:26</a>).</p></div>"
  } ]
}, {
  "singleVerses" : [ "acts,1,5" ],
  "rsbNotes" : [ {
    "verseRange" : "acts,1,5",
    "id" : 197349,
    "title" : "Acts 1:5",
    "text" : "<div class=\"article\"><p><b><a class=\"bibleref\" href=\"/passage/?search=Acts 1:5\">1:5</a></b> <b>John baptized with water</b>. John the Baptist baptized large crowds of people (<a class=\"bibleref\" href=\"/passage/?search=Matt 3:5\">Matt. 3:5</a>, <a class=\"bibleref\" href=\"/passage/?search=Matt 3:6\">6</a>, <a class=\"bibleref\" href=\"/passage/?search=Matt 3:13-Matt 3:15\">13–15</a>; <a class=\"bibleref\" href=\"/passage/?search=Mark 1:5\">Mark 1:5</a>, <a class=\"bibleref\" href=\"/passage/?search=Mark 1:9\">9</a>; <a class=\"bibleref\" href=\"/passage/?search=Luke 3:7-Luke 3:16\">Luke 3:7–16</a>, <a class=\"bibleref\" href=\"/passage/?search=Luke 3:21\">21</a>). John’s water baptism of repentance (<a class=\"bibleref\" href=\"/passage/?search=Mark 1:4\">Mark 1:4</a>) pointed forward to the messianic baptism with the Holy Spirit and fire (<a class=\"bibleref\" href=\"/passage/?search=Luke 3:16\">Luke 3:16</a>). See “The Baptism of Jesus” at <a class=\"bibleref\" href=\"/passage/?search=Mark 1:9\">Mark 1:9</a>.</p><p><b>not many days from now.</b> A few days would pass before Pentecost.</p></div>"
  } ]
}, {
  "singleVerses" : [ "acts,1,6" ],
  "rsbNotes" : [ {
    "verseRange" : "acts,1,6",
    "id" : 197350,
    "title" : "Acts 1:6",
    "text" : "<div class=\"article\"><p><b><a class=\"bibleref\" href=\"/passage/?search=Acts 1:6\">1:6</a></b> <b>at this time restore the kingdom to Israel.</b> From what Jesus said in <a class=\"bibleref\" href=\"/passage/?search=Matt 19:28\">Matt. 19:28</a>, the disciples thought that He might overthrow the Romans and restore the physical kingdom to Israel.</p></div>"
  } ]
}, {
  "singleVerses" : [ "acts,1,7" ],
  "rsbNotes" : [ {
    "verseRange" : "acts,1,7",
    "id" : 197351,
    "title" : "Acts 1:7",
    "text" : "<div class=\"article\"><p><b><a class=\"bibleref\" href=\"/passage/?search=Acts 1:7\">1:7</a></b> <b>not for you to know times or seasons.</b> The specific years or dates (which some in all ages try to predict) of the Second Coming of Christ (cf. <a class=\"bibleref\" href=\"/passage/?search=1Thess 5:2\">1 Thess. 5:2</a>).</p></div>"
  } ]
}, {
  "singleVerses" : [ "acts,1,8" ],
  "rsbNotes" : [ {
    "verseRange" : "acts,1,8",
    "id" : 197352,
    "title" : "Acts 1:8",
    "text" : "<div class=\"article\"><p><b><a class=\"bibleref\" href=\"/passage/?search=Acts 1:8\">1:8</a></b> <b>Holy Spirit has come upon you.</b> Jesus means that the Holy Spirit will show His control of their lives with visible manifestations: the blowing of a violent wind, the appearance of tongues of fire, and speaking in foreign languages (<a class=\"bibleref\" href=\"/passage/?search=Acts 2\">ch. 2</a>).</p><p><b>my witnesses in Jerusalem and in all Judea and Samaria, and to the end of the earth.</b> The Book of Acts follows this strategy. The Jerusalem witness (<a class=\"bibleref\" href=\"/passage/?search=Acts 2\">ch. 2</a>) gives in miniature form God’s worldwide ministry: the “Jews . . . from every nation” (<a class=\"bibleref\" href=\"/passage/?search=Acts 2:5\">2:5</a>) who heard and believed carried the message far and wide. In the rest of Acts the gospel spreads to Jerusalem (<a class=\"bibleref\" href=\"/passage/?search=Acts 3:1-Acts 8:1\">3:1–8:1</a>), to Judea and Samaria, up to Antioch of Syria (<a class=\"bibleref\" href=\"/passage/?search=Acts 8-Acts 12\">8:1–12:25</a>), and to the ends of the earth (<a class=\"bibleref\" href=\"/passage/?search=Acts 13-Acts 28\">13:1–28:31</a>).</p></div>"
  } ]
}, {
  "singleVerses" : [ "acts,1,9" ],
  "rsbNotes" : [ {
    "verseRange" : "acts,1,9",
    "id" : 197353,
    "title" : "Acts 1:9",
    "text" : "<div class=\"article\"><p><b><a class=\"bibleref\" href=\"/passage/?search=Acts 1:9\">1:9</a></b> <b>he was lifted up.</b> See “The Ascension of Jesus” at <a class=\"bibleref\" href=\"/passage/?search=Luke 24:51\">Luke 24:51</a>.</p></div>"
  } ]
}, {
  "singleVerses" : [ "acts,1,10" ],
  "rsbNotes" : [ {
    "verseRange" : "acts,1,10",
    "id" : 197354,
    "title" : "Acts 1:10",
    "text" : "<div class=\"article\"><p><b><a class=\"bibleref\" href=\"/passage/?search=Acts 1:10\">1:10</a></b> <b>two men . . . in white robes.</b> Persons described as dressed in white are commonly supernatural or glorified beings: Jesus Christ (<a class=\"bibleref\" href=\"/passage/?search=Matt 17:2\">Matt. 17:2</a>; <a class=\"bibleref\" href=\"/passage/?search=Mark 9:3\">Mark 9:3</a>; <a class=\"bibleref\" href=\"/passage/?search=Rev 1:14\">Rev. 1:14</a>), angels (<a class=\"bibleref\" href=\"/passage/?search=Matt 28:3\">Matt. 28:3</a>; <a class=\"bibleref\" href=\"/passage/?search=Mark 16:5\">Mark 16:5</a>; <a class=\"bibleref\" href=\"/passage/?search=Luke 24:4\">Luke 24:4</a>; <a class=\"bibleref\" href=\"/passage/?search=John 20:12\">John 20:12</a>), and glorified saints (<a class=\"bibleref\" href=\"/passage/?search=Luke 9:30\">Luke 9:30</a>, <a class=\"bibleref\" href=\"/passage/?search=Luke 9:31\">31</a>; <a class=\"bibleref\" href=\"/passage/?search=Rev 3:4\">Rev. 3:4</a>, <a class=\"bibleref\" href=\"/passage/?search=Rev 3:5\">5</a>, <a class=\"bibleref\" href=\"/passage/?search=Rev 3:18\">18</a>; <a class=\"bibleref\" href=\"/passage/?search=Rev 4:4\">4:4</a>; <a class=\"bibleref\" href=\"/passage/?search=Rev 7:14\">7:14</a>).</p></div>"
  } ]
}, {
  "singleVerses" : [ "acts,1,11" ],
  "rsbNotes" : [ {
    "verseRange" : "acts,1,11",
    "id" : 197355,
    "title" : "Acts 1:11",
    "text" : "<div class=\"article\"><p><b><a class=\"bibleref\" href=\"/passage/?search=Acts 1:11\">1:11</a></b> <b>Men of Galilee.</b> The eleven were from Galilee; Judas Iscariot was from Kerioth in Judah.</p><p><b>in the same way.</b> Jesus will return in His resurrection body, coming with the clouds of heaven (<a class=\"bibleref\" href=\"/passage/?search=Matt 24:30\">Matt. 24:30</a>; <a class=\"bibleref\" href=\"/passage/?search=Matt 26:64\">26:64</a>; <a class=\"bibleref\" href=\"/passage/?search=Mark 14:62\">Mark 14:62</a>; <a class=\"bibleref\" href=\"/passage/?search=1Thess 4:16\">1 Thess. 4:16</a>, <a class=\"bibleref\" href=\"/passage/?search=1Thess 4:17\">17</a>; <a class=\"bibleref\" href=\"/passage/?search=Rev 1:7\">Rev. 1:7</a>). See “The Return of Christ” at <a class=\"bibleref\" href=\"/passage/?search=1Thess 4:16\">1 Thess. 4:16</a>.</p></div>"
  } ]
}, {
  "singleVerses" : [ "acts,1,12" ],
  "rsbNotes" : [ {
    "verseRange" : "acts,1,12",
    "id" : 197356,
    "title" : "Acts 1:12",
    "text" : "<div class=\"article\"><p><b><a class=\"bibleref\" href=\"/passage/?search=Acts 1:12\">1:12</a></b> <b>the mount called Olivet.</b> A hill beyond the Kidron Valley just east of the walled city of Jerusalem. The disciples had been with Jesus on the Mount near Bethany (<a class=\"bibleref\" href=\"/passage/?search=Luke 24:50\">Luke 24:50</a>).</p><p><b>a Sabbath day’s journey.</b> From the city, a distance calculated by the rabbis to be about 1,100 meters or three-fourths of a mile.</p></div>"
  } ]
}, {
  "singleVerses" : [ "acts,1,13" ],
  "rsbNotes" : [ {
    "verseRange" : "acts,1,13",
    "id" : 197357,
    "title" : "Acts 1:13",
    "text" : "<div class=\"article\"><p><b><a class=\"bibleref\" href=\"/passage/?search=Acts 1:13\">1:13</a></b> <b>up to the upper room, where they were staying.</b> Probably where the disciples had been hiding for fear of the Jews. This may have been the same room in which they had celebrated the Passover and Jesus had instituted the Lord’s Supper (<a class=\"bibleref\" href=\"/passage/?search=Mark 14:15\">Mark 14:15</a>), or a room in the house of Mary, the aunt of Barnabas (<a class=\"bibleref\" href=\"/passage/?search=Col 4:10\">Col. 4:10</a>), where the Christians later held meetings (12:12). It was probably located close to the temple courts where the visiting Jewish crowds were assembled (2:5–12).</p><p><b>Bartholomew.</b> Also known as Nathanael (<a class=\"bibleref\" href=\"/passage/?search=John 1:45\">John 1:45</a>; <a class=\"bibleref\" href=\"/passage/?search=John 21:2\">21:2</a>).</p><p><b>James the son of Alphaeus.</b> Also known as James the younger (<a class=\"bibleref\" href=\"/passage/?search=Mark 15:40\">Mark 15:40</a>).</p><p><b>Zealot.</b> Possibly referring to Simon’s former membership in the Zealot revolutionary group.</p><p><b>Judas the son of James.</b> Also known as Thaddaeus (<a class=\"bibleref\" href=\"/passage/?search=Matt 10:3\">Matt. 10:3</a>; <a class=\"bibleref\" href=\"/passage/?search=Mark 3:18\">Mark 3:18</a>).</p></div>"
  } ]
}, {
  "singleVerses" : [ "acts,1,14" ],
  "rsbNotes" : [ {
    "verseRange" : "acts,1,14",
    "id" : 197358,
    "title" : "Acts 1:14",
    "text" : "<div class=\"article\"><p><b><a class=\"bibleref\" href=\"/passage/?search=Acts 1:14\">1:14</a></b> <b>devoting themselves to prayer.</b> Jesus established a pattern of prayer in the lives of His disciples. For examples of Jesus praying, see <a class=\"bibleref\" href=\"/passage/?search=Luke 3:21\">Luke 3:21</a>; <a class=\"bibleref\" href=\"/passage/?search=Luke 5:16\">5:16</a>; <a class=\"bibleref\" href=\"/passage/?search=Luke 6:12\">6:12</a>; <a class=\"bibleref\" href=\"/passage/?search=Luke 9:18\">9:18</a>, <a class=\"bibleref\" href=\"/passage/?search=Luke 9:28\">28</a>, <a class=\"bibleref\" href=\"/passage/?search=Luke 9:29\">29</a>; <a class=\"bibleref\" href=\"/passage/?search=Luke 11:1\">11:1</a>; <a class=\"bibleref\" href=\"/passage/?search=Luke 22:32\">22:32</a>, <a class=\"bibleref\" href=\"/passage/?search=Luke 22:41\">41</a>; <a class=\"bibleref\" href=\"/passage/?search=Luke 23:34\">23:34</a>, <a class=\"bibleref\" href=\"/passage/?search=Luke 23:46\">46</a>.</p><p><b>with the women.</b> Certain women who had followed Jesus, supported His work, and cared for Him in His death (<a class=\"bibleref\" href=\"/passage/?search=Matt 27:55\">Matt. 27:55</a>, <a class=\"bibleref\" href=\"/passage/?search=Matt 27:56\">56</a>; <a class=\"bibleref\" href=\"/passage/?search=Matt 28:1\">28:1</a>; <a class=\"bibleref\" href=\"/passage/?search=Mark 15:40\">Mark 15:40</a>, <a class=\"bibleref\" href=\"/passage/?search=Mark 15:41\">41</a>; <a class=\"bibleref\" href=\"/passage/?search=Luke 8:2\">Luke 8:2</a>, <a class=\"bibleref\" href=\"/passage/?search=Luke 8:3\">3</a>; <a class=\"bibleref\" href=\"/passage/?search=Luke 23:49\">23:49</a>; <a class=\"bibleref\" href=\"/passage/?search=Luke 24:1\">24:1</a>, <a class=\"bibleref\" href=\"/passage/?search=Luke 24:22\">22</a>).</p><p><b>Mary the mother of Jesus.</b> This is the last reference in the New Testament to Jesus’ mother.</p><p><b>his brothers.</b> Jesus’ half brothers, the sons of Mary and Joseph (<a class=\"bibleref\" href=\"/passage/?search=Matt 13:55\">Matt. 13:55</a>; <a class=\"bibleref\" href=\"/passage/?search=Luke 14:26\">Luke 14:26</a>; <a class=\"bibleref\" href=\"/passage/?search=John 7:3\">John 7:3</a>, <a class=\"bibleref\" href=\"/passage/?search=John 7:10\">10</a>).</p></div>"
  } ]
}, {
  "singleVerses" : [ "acts,1,15" ],
  "rsbNotes" : [ {
    "verseRange" : "acts,1,15",
    "id" : 197359,
    "title" : "Acts 1:15",
    "text" : "<div class=\"article\"><p><b><a class=\"bibleref\" href=\"/passage/?search=Acts 1:15\">1:15</a></b> <b>In those days.</b> The ten days between the Ascension and Pentecost (<a class=\"bibleref\" href=\"/passage/?search=Acts 2:1\">2:1</a>).</p></div>"
  } ]
}, {
  "singleVerses" : [ "acts,1,16" ],
  "rsbNotes" : [ {
    "verseRange" : "acts,1,16",
    "id" : 197360,
    "title" : "Acts 1:16",
    "text" : "<div class=\"article\"><p><b><a class=\"bibleref\" href=\"/passage/?search=Acts 1:16\">1:16</a></b> <b>Brothers.</b> Males are particularly addressed here because Peter is talking about replacing Judas Iscariot, one of the Twelve whom Jesus had originally chosen as apostles (<a class=\"bibleref\" href=\"/passage/?search=Matt 10:2-Matt 10:4\">Matt. 10:2–4</a>).</p><p><b>the Scripture had to be fulfilled.</b> <a class=\"bibleref\" href=\"/passage/?search=Ps 69:25\">Ps. 69:25</a> and <a class=\"bibleref\" href=\"/passage/?search=Ps 109:8\">109:8</a>, quoted in v. 20, are applied by Peter to Judas Iscariot, who as an enemy of God had been deposed from his apostleship. Now “his office” (<a class=\"bibleref\" href=\"/passage/?search=Ps 109:8\">Ps. 109:8</a>) had to be filled again.</p><p><b>the Holy Spirit spoke . . . by the mouth of David.</b> The Holy Spirit inspired David to compose these words using his poetic skills.</p></div>"
  } ]
}, {
  "singleVerses" : [ "acts,1,17" ],
  "rsbNotes" : [ {
    "verseRange" : "acts,1,17",
    "id" : 197361,
    "title" : "Acts 1:17",
    "text" : "<div class=\"article\"><p><b><a class=\"bibleref\" href=\"/passage/?search=Acts 1:17\">1:17</a></b> <b>allotted his share in this ministry.</b> In His plan God allowed Judas, the enemy of the Savior, to serve for a time in the ministry of the disciples.</p></div>"
  } ]
}, {
  "singleVerses" : [ "acts,1,18", "acts,1,19", "acts,1,20" ],
  "rsbNotes" : [ {
    "verseRange" : "acts,1,18",
    "id" : 197362,
    "title" : "Acts 1:18",
    "text" : "<div class=\"article\"><p><b><a class=\"bibleref\" href=\"/passage/?search=Acts 1:18\">1:18</a></b> <b>this man bought a field.</b> Judas indirectly bought the field when he returned the money to the chief priests and elders who in turn purchased a burial place for foreigners called “Field of Blood.”</p><p><b>with the reward.</b> The thirty silver coins (<a class=\"bibleref\" href=\"/passage/?search=Matt 26:15\">Matt. 26:15</a>), probably worth about 120 denarii, or 120 days’ labor (<a class=\"bibleref\" href=\"/passage/?search=Matt 20:2\">Matt. 20:2</a>).</p><p><b>falling headlong.</b> Matthew writes that Judas “hanged himself” (<a class=\"bibleref\" href=\"/passage/?search=Matt 27:5\">Matt. 27:5</a>). Apparently during or soon after the hanging his body fell to the ground and was broken or decomposed.</p></div>"
  } ]
}, {
  "singleVerses" : [ "acts,1,21", "acts,1,22" ],
  "rsbNotes" : [ {
    "verseRange" : "acts,1,21",
    "id" : 197363,
    "title" : "Acts 1:21",
    "text" : "<div class=\"article\"><p><b><a class=\"bibleref\" href=\"/passage/?search=Acts 1:21\">1:21</a></b> <b>among us.</b> This includes the whole time of Jesus’ public ministry from His baptism to His ascension.</p></div>"
  } ]
}, {
  "singleVerses" : [ "acts,1,23" ],
  "rsbNotes" : [ {
    "verseRange" : "acts,1,23",
    "id" : 197364,
    "title" : "Acts 1:23",
    "text" : "<div class=\"article\"><p><b><a class=\"bibleref\" href=\"/passage/?search=Acts 1:23\">1:23</a></b> <b>put forward two.</b> Evidently Joseph and Matthias were chosen from a larger number of witnesses (according to <a class=\"bibleref\" href=\"/passage/?search=Acts 1:15\">v. 15</a>, about 120 persons were present). Neither is mentioned elsewhere in Scripture.</p></div>"
  } ]
}, {
  "singleVerses" : [ "acts,1,24", "acts,1,25" ],
  "rsbNotes" : [ {
    "verseRange" : "acts,1,24",
    "id" : 197365,
    "title" : "Acts 1:24",
    "text" : "<div class=\"article\"><p><b><a class=\"bibleref\" href=\"/passage/?search=Acts 1:24\">1:24</a></b> <b>you have chosen.</b> Peter and the disciples recognized that their human responsibility and choice of a man to succeed Judas occurred within the bounds of God’s sovereign will.</p></div>"
  } ]
}, {
  "singleVerses" : [ "acts,1,26" ],
  "rsbNotes" : [ {
    "verseRange" : "acts,1,26",
    "id" : 197366,
    "title" : "Acts 1:26",
    "text" : "<div class=\"article\"><p><b><a class=\"bibleref\" href=\"/passage/?search=Acts 1:26\">1:26</a></b> <b>cast lots.</b> Lots are mentioned in the Old Testament as a means of ascertaining God’s will (<a class=\"bibleref\" href=\"/passage/?search=Exod 28:30\">Ex. 28:30</a> note).</p><p><b>apostles.</b> See theological note “The Apostles” on the next page.</p></div>"
  } ]
} ]
