[ {
  "singleVerses" : [ "ecclesiastes,10,1" ],
  "rsbNotes" : [ ]
}, {
  "singleVerses" : [ "ecclesiastes,10,2", "ecclesiastes,10,3", "ecclesiastes,10,4" ],
  "rsbNotes" : [ {
    "verseRange" : "ecclesiastes,10,2",
    "id" : 192466,
    "title" : "Eccl 10:2",
    "text" : "<div class=\"article\"><p><b><a class=\"bibleref\" href=\"/passage/?search=Eccl 10:2\">10:2</a></b> <b>right . . . left.</b> These had the conventional meanings of good and bad, or blessing and cursing, in the ancient world.</p></div>"
  } ]
}, {
  "singleVerses" : [ "ecclesiastes,10,5", "ecclesiastes,10,6", "ecclesiastes,10,7", "ecclesiastes,10,8", "ecclesiastes,10,9" ],
  "rsbNotes" : [ {
    "verseRange" : "ecclesiastes,10,5",
    "id" : 192467,
    "title" : "Eccl 10:5",
    "text" : "<div class=\"article\"><p><b><a class=\"bibleref\" href=\"/passage/?search=Eccl 10:5\">10:5</a></b> <b>error.</b> Rulers often govern inappropriately.</p></div>"
  } ]
}, {
  "singleVerses" : [ "ecclesiastes,10,10", "ecclesiastes,10,11" ],
  "rsbNotes" : [ {
    "verseRange" : "ecclesiastes,10,10",
    "id" : 192468,
    "title" : "Eccl 10:10",
    "text" : "<div class=\"article\"><p><b><a class=\"bibleref\" href=\"/passage/?search=Eccl 10:10\">10:10</a></b> <b>sharpen the edge.</b> Overcome the obstacles to effective work by being properly prepared with the wisdom or skill needed for the task.</p></div>"
  } ]
}, {
  "singleVerses" : [ "ecclesiastes,10,12", "ecclesiastes,10,13", "ecclesiastes,10,14", "ecclesiastes,10,15", "ecclesiastes,10,16", "ecclesiastes,10,17", "ecclesiastes,10,18" ],
  "rsbNotes" : [ {
    "verseRange" : "ecclesiastes,10,12-ecclesiastes,10,14",
    "id" : 192469,
    "title" : "Eccl 10:12–14",
    "text" : "<div class=\"article\"><p><b><a class=\"bibleref\" href=\"/passage/?search=Eccl 10:12-Eccl 10:14\">10:12–14</a></b> <b>words.</b> Words reveal a person’s heart, and what is spoken can have serious consequences (<a class=\"bibleref\" href=\"/passage/?search=Matt 12:34-Matt 12:37\">Matt. 12:34–37</a>).</p></div>"
  } ]
}, {
  "singleVerses" : [ "ecclesiastes,10,19" ],
  "rsbNotes" : [ {
    "verseRange" : "ecclesiastes,10,19",
    "id" : 192470,
    "title" : "Eccl 10:19",
    "text" : "<div class=\"article\"><p><b><a class=\"bibleref\" href=\"/passage/?search=Eccl 10:19\">10:19</a></b> <b>everything.</b> This can mean that money is needed for both food and wine, or that money provides life’s needs (cf. <a class=\"bibleref\" href=\"/passage/?search=Eccl 7:12\">7:12</a>).</p></div>"
  } ]
}, {
  "singleVerses" : [ "ecclesiastes,10,20" ],
  "rsbNotes" : [ {
    "verseRange" : "ecclesiastes,10,20",
    "id" : 192471,
    "title" : "Eccl 10:20",
    "text" : "<div class=\"article\"><p><b><a class=\"bibleref\" href=\"/passage/?search=Eccl 10:20\">10:20</a></b> <b>bird.</b> A figure of speech meaning a spy or an informer.</p></div>"
  } ]
}, {
  "singleVerses" : [ "ecclesiastes,11,1" ],
  "rsbNotes" : [ {
    "verseRange" : "ecclesiastes,11,1",
    "id" : 192472,
    "title" : "Eccl 11:1",
    "text" : "<div class=\"article\"><p><b><a class=\"bibleref\" href=\"/passage/?search=Eccl 11:1\">11:1</a></b> <b>bread upon the waters.</b> Possibly a reference to Solomon’s grain trade by sea.</p></div>"
  } ]
}, {
  "singleVerses" : [ "ecclesiastes,11,2" ],
  "rsbNotes" : [ {
    "verseRange" : "ecclesiastes,11,2",
    "id" : 192473,
    "title" : "Eccl 11:2",
    "text" : "<div class=\"article\"><p><b><a class=\"bibleref\" href=\"/passage/?search=Eccl 11:2\">11:2</a></b> <b>seven . . . eight.</b> An admonition to spread the risks you take (<a class=\"bibleref\" href=\"/passage/?search=Eccl 11:6\">v. 6</a>).</p><p><b>you know not.</b> Uncertainty is a reason for diversity in financial management. See <a class=\"bibleref\" href=\"/passage/?search=Eccl 11:6\">v. 6</a>.</p></div>"
  } ]
}, {
  "singleVerses" : [ "ecclesiastes,11,3", "ecclesiastes,11,4" ],
  "rsbNotes" : [ {
    "verseRange" : "ecclesiastes,11,3-ecclesiastes,11,4",
    "id" : 192474,
    "title" : "Eccl 11:3–4",
    "text" : "<div class=\"article\"><p><b><a class=\"bibleref\" href=\"/passage/?search=Eccl 11:3\">11:3</a>, <a class=\"bibleref\" href=\"/passage/?search=Eccl 11:4\">4</a> clouds.</b> Do not use uncertainty as an excuse for laziness.</p></div>"
  } ]
}, {
  "singleVerses" : [ "ecclesiastes,11,5" ],
  "rsbNotes" : [ {
    "verseRange" : "ecclesiastes,11,5",
    "id" : 192475,
    "title" : "Eccl 11:5",
    "text" : "<div class=\"article\"><p><b><a class=\"bibleref\" href=\"/passage/?search=Eccl 11:5\">11:5</a></b> <b>work of God.</b> Here again is an affirmation of God’s incomprehensible, secret counsel (<a class=\"bibleref\" href=\"/passage/?search=Eccl 8:17\">8:17</a> note).</p></div>"
  } ]
}, {
  "singleVerses" : [ "ecclesiastes,11,6" ],
  "rsbNotes" : [ {
    "verseRange" : "ecclesiastes,11,6",
    "id" : 192476,
    "title" : "Eccl 11:6",
    "text" : "<div class=\"article\"><p><b><a class=\"bibleref\" href=\"/passage/?search=Eccl 11:6\">11:6</a></b> <b>do not know.</b> See note on <a class=\"bibleref\" href=\"/passage/?search=Eccl 11:2\">v. 2</a>.</p></div>"
  } ]
}, {
  "singleVerses" : [ "ecclesiastes,11,7" ],
  "rsbNotes" : [ {
    "verseRange" : "ecclesiastes,11,7-ecclesiastes,12,7",
    "id" : 192477,
    "title" : "Eccl 11:7–12:7",
    "text" : "<div class=\"article\"><p><b><a class=\"bibleref\" href=\"/passage/?search=Eccl 11:7-Eccl 12:7\">11:7–12:7</a></b> Natural, youthful life is to be governed with discretion, because this present life will be followed by a certain meeting with God (<a class=\"bibleref\" href=\"/passage/?search=Eccl 12:8\">12:8</a>).</p></div>"
  } ]
}, {
  "singleVerses" : [ "ecclesiastes,11,8" ],
  "rsbNotes" : [ {
    "verseRange" : "ecclesiastes,11,8",
    "id" : 192478,
    "title" : "Eccl 11:8",
    "text" : "<div class=\"article\"><p><b><a class=\"bibleref\" href=\"/passage/?search=Eccl 11:8\">11:8</a></b> <b>rejoice . . . remember.</b> The joys of present life should be held loosely, in the awareness that such joy is temporary.</p></div>"
  } ]
}, {
  "singleVerses" : [ "ecclesiastes,11,9", "ecclesiastes,11,10" ],
  "rsbNotes" : [ {
    "verseRange" : "ecclesiastes,11,9",
    "id" : 192479,
    "title" : "Eccl 11:9",
    "text" : "<div class=\"article\"><p><b><a class=\"bibleref\" href=\"/passage/?search=Eccl 11:9\">11:9</a></b> <b>judgment.</b> Solomon does not encourage mindless self-indulgence, but gives a sober warning that God will bring everything into judgment (<a class=\"bibleref\" href=\"/passage/?search=Matt 12:36\">Matt. 12:36</a>).</p></div>"
  } ]
}, {
  "singleVerses" : [ "ecclesiastes,12,1" ],
  "rsbNotes" : [ {
    "verseRange" : "ecclesiastes,12,1",
    "id" : 192480,
    "title" : "Eccl 12:1",
    "text" : "<div class=\"article\"><p><b><a class=\"bibleref\" href=\"/passage/?search=Eccl 12:1\">12:1</a></b> <b>evil days.</b> If pleasure is unrestrained in youth, both pleasure and the Creator will be unknown in later years.</p></div>"
  } ]
}, {
  "singleVerses" : [ "ecclesiastes,12,2" ],
  "rsbNotes" : [ {
    "verseRange" : "ecclesiastes,12,2-ecclesiastes,12,7",
    "id" : 192481,
    "title" : "Eccl 12:2–7",
    "text" : "<div class=\"article\"><p><b><a class=\"bibleref\" href=\"/passage/?search=Eccl 12:2-Eccl 12:7\">12:2–7</a></b> Solomon comments on aging and death, using the extended metaphor of a house that is falling down. He contrasts the deterioration of the house with the permanence of nature. It is best to take the metaphors here for their overall effect, rather than speculate on the meaning of each individual figure. As the following notes indicate, some associations are clearer than others.</p></div>"
  } ]
}, {
  "singleVerses" : [ "ecclesiastes,12,3", "ecclesiastes,12,4" ],
  "rsbNotes" : [ {
    "verseRange" : "ecclesiastes,12,3",
    "id" : 192482,
    "title" : "Eccl 12:3",
    "text" : "<div class=\"article\"><p><b><a class=\"bibleref\" href=\"/passage/?search=Eccl 12:3\">12:3</a></b> <b>keepers of the house.</b> The phrases here probably refer to parts of the body as members of a household.</p></div>"
  } ]
}, {
  "singleVerses" : [ "ecclesiastes,12,5" ],
  "rsbNotes" : [ {
    "verseRange" : "ecclesiastes,12,5",
    "id" : 192483,
    "title" : "Eccl 12:5",
    "text" : "<div class=\"article\"><p><b><a class=\"bibleref\" href=\"/passage/?search=Eccl 12:5\">12:5</a></b> <b>the almond tree blossoms.</b> Their white color is associated with the hair of the aged.</p><p><b>eternal home.</b> The words refer not just to the grave, but to the presence of one’s Creator and Judge (<a class=\"bibleref\" href=\"/passage/?search=Eccl 12:7\">v. 7</a>).</p></div>"
  } ]
}, {
  "singleVerses" : [ "ecclesiastes,12,6" ],
  "rsbNotes" : [ {
    "verseRange" : "ecclesiastes,12,6",
    "id" : 192484,
    "title" : "Eccl 12:6",
    "text" : "<div class=\"article\"><p><b><a class=\"bibleref\" href=\"/passage/?search=Eccl 12:6\">12:6</a></b> <b>golden bowl.</b> These words describe a lamp broken in the fall caused by a break in a silver chain. Broken vessels and severed cords suggest the frailty that comes with aging.</p></div>"
  } ]
}, {
  "singleVerses" : [ "ecclesiastes,12,7" ],
  "rsbNotes" : [ {
    "verseRange" : "ecclesiastes,12,7",
    "id" : 192485,
    "title" : "Eccl 12:7",
    "text" : "<div class=\"article\"><p><b><a class=\"bibleref\" href=\"/passage/?search=Eccl 12:7\">12:7</a></b> <b>the spirit returns.</b> Human existence continues beyond death.</p></div>"
  } ]
}, {
  "singleVerses" : [ "ecclesiastes,12,8" ],
  "rsbNotes" : [ {
    "verseRange" : "ecclesiastes,12,8",
    "id" : 192486,
    "title" : "Eccl 12:8",
    "text" : "<div class=\"article\"><p><b><a class=\"bibleref\" href=\"/passage/?search=Eccl 12:8\">12:8</a></b> <b>Vanity.</b> A final reiteration of the Preacher’s refrain.</p></div>"
  } ]
}, {
  "singleVerses" : [ "ecclesiastes,12,9", "ecclesiastes,12,10" ],
  "rsbNotes" : [ {
    "verseRange" : "ecclesiastes,12,9-ecclesiastes,12,14",
    "id" : 192487,
    "title" : "Eccl 12:9–14",
    "text" : "<div class=\"article\"><p><b><a class=\"bibleref\" href=\"/passage/?search=Eccl 12:9-Eccl 12:14\">12:9–14</a></b> The book concludes with a tribute to Solomon’s wisdom, providing the keys to interpreting the book.</p></div>"
  } ]
}, {
  "singleVerses" : [ "ecclesiastes,12,11", "ecclesiastes,12,12" ],
  "rsbNotes" : [ {
    "verseRange" : "ecclesiastes,12,11",
    "id" : 192488,
    "title" : "Eccl 12:11",
    "text" : "<div class=\"article\"><p><b><a class=\"bibleref\" href=\"/passage/?search=Eccl 12:11\">12:11</a></b> <b>given by one Shepherd.</b> The words of Ecclesiastes are God-breathed (<a class=\"bibleref\" href=\"/passage/?search=2Tim 3:16\">2 Tim. 3:16</a>).</p></div>"
  } ]
}, {
  "singleVerses" : [ "ecclesiastes,12,13" ],
  "rsbNotes" : [ {
    "verseRange" : "ecclesiastes,12,13",
    "id" : 192489,
    "title" : "Eccl 12:13",
    "text" : "<div class=\"article\"><p><b><a class=\"bibleref\" href=\"/passage/?search=Eccl 12:13\">12:13</a></b> <b>end of the matter.</b> Loyal submission to the rule of God is the central and summary admonition of wisdom literature (<a class=\"bibleref\" href=\"/passage/?search=Eccl 5:7\">5:7</a>; <a class=\"bibleref\" href=\"/passage/?search=Job 28:28\">Job 28:28</a>; <a class=\"bibleref\" href=\"/passage/?search=Prov 1:7\">Prov. 1:7</a>; <a class=\"bibleref\" href=\"/passage/?search=Prov 9:10\">9:10</a>).</p></div>"
  } ]
}, {
  "singleVerses" : [ "ecclesiastes,12,14" ],
  "rsbNotes" : [ {
    "verseRange" : "ecclesiastes,12,14",
    "id" : 192490,
    "title" : "Eccl 12:14",
    "text" : "<div class=\"article\"><p><b><a class=\"bibleref\" href=\"/passage/?search=Eccl 12:14\">12:14</a></b> <b>judgment.</b> God’s judgment of thoughts and deeds is a dominant theme that emerges throughout the book (<a class=\"bibleref\" href=\"/passage/?search=Eccl 3:17\">3:17</a>; <a class=\"bibleref\" href=\"/passage/?search=Eccl 8:12\">8:12</a>, <a class=\"bibleref\" href=\"/passage/?search=Eccl 8:13\">13</a>; <a class=\"bibleref\" href=\"/passage/?search=Eccl 11:9\">11:9</a>; <a class=\"bibleref\" href=\"/passage/?search=2Cor 5:10\">2 Cor. 5:10</a>).</p></div>"
  } ]
} ]
